MANIFEST.in
README.md
setup.py
gitpyman/Client.py
gitpyman/Client.ui
gitpyman/Ui_Client.py
gitpyman/__init__.py
gitpyman/gm_run.py
gitpyman/res_rc.py
gitpyman.egg-info/PKG-INFO
gitpyman.egg-info/SOURCES.txt
gitpyman.egg-info/dependency_links.txt
gitpyman.egg-info/entry_points.txt
gitpyman.egg-info/not-zip-safe
gitpyman.egg-info/requires.txt
gitpyman.egg-info/top_level.txt
gitpyman/Data/_qwebchannel.js
gitpyman/Data/babel_.cmd
gitpyman/Data/jquery-3.3.1.min.js
gitpyman/Data/qwebchannel.js
gitpyman/Data/res.qrc
gitpyman/Data/run_in_web.js
gitpyman/UUI/Base_TableView.py
gitpyman/UUI/Base_TableView_Delegate.py
gitpyman/UUI/Serve.py
gitpyman/UUI/Serve.ui
gitpyman/UUI/Ui_Serve.py
gitpyman/UUI/__init__.py
gitpyman/UUI/main_db_control.py
gitpyman/UUI/main_db_control_util1.py
gitpyman/UUI/main_db_model.py
gitpyman/UUI_WEB/__init__.py
gitpyman/UUI_WEB/webComponent.py
gitpyman/UUI_WEB/webControl.py
gitpyman/UUI_WEB/webSharedObject.py
gitpyman/hgoldfish/__init__.py
gitpyman/hgoldfish/examples/__init__.py
gitpyman/hgoldfish/examples/gate.py
gitpyman/hgoldfish/examples/getgoogle.py
gitpyman/hgoldfish/examples/use_requests.py
gitpyman/hgoldfish/examples/yield_from.py
gitpyman/hgoldfish/utils/__init__.py
gitpyman/hgoldfish/utils/eventlet.py
gitpyman/util/BasePara.py
gitpyman/util/Task.py
gitpyman/util/__init__.py
gitpyman/util/github.py
gitpyman/util/runTest.py