Metadata-Version: 2.1
Name: gitpyman
Version: 0.0.6
Summary: comment your github.
Home-page: https://github.com/625781186/gitpyman
Author: Lin JH
Author-email: 625781186@qq.com
License: GPL-3.0
Keywords: python、PyQt5、github Manage
Platform: UNKNOWN
Requires-Python: >=3.6
